Newsroom-1.0.data/scripts/manage.py
Newsroom-1.0.dist-info/METADATA
Newsroom-1.0.dist-info/RECORD
Newsroom-1.0.dist-info/WHEEL
Newsroom-1.0.dist-info/top_level.txt
newsroom/__init__.py
newsroom/app.py
newsroom/default_settings.py
newsroom/design.py
newsroom/elastic_utils.py
newsroom/email.py
newsroom/flaskapp.py
newsroom/history.py
newsroom/mongo_utils.py
newsroom/push.py
newsroom/template_filters.py
newsroom/upload.py
newsroom/utils.py
newsroom/webpack.py
newsroom/websocket.py
newsroom/wsgi.py
newsroom/auth/__init__.py
newsroom/auth/decorator.py
newsroom/auth/forms.py
newsroom/auth/token.py
newsroom/auth/views.py
newsroom/cards/__init__.py
newsroom/cards/cards.py
newsroom/cards/views.py
newsroom/companies/__init__.py
newsroom/companies/companies.py
newsroom/companies/views.py
newsroom/navigations/__init__.py
newsroom/navigations/navigations.py
newsroom/navigations/views.py
newsroom/notifications/__init__.py
newsroom/notifications/notifications.py
newsroom/products/__init__.py
newsroom/products/products.py
newsroom/products/views.py
newsroom/public/__init__.py
newsroom/public/views.py
newsroom/reports/__init__.py
newsroom/reports/reports.py
newsroom/reports/views.py
newsroom/static/arrow-right-black.svg
newsroom/static/article_preview.png
newsroom/static/favicon.ico
newsroom/static/icon-arrow-white.svg
newsroom/static/icon-external-link-blue.svg
newsroom/static/image-icon.png
newsroom/static/item_detail_img.jpg
newsroom/static/list_icon.png
newsroom/static/list_image.png
newsroom/static/list_image_800x600.jpg
newsroom/static/logo-aap-photos-x2.png
newsroom/static/logo-aap-photos.png
newsroom/static/logo-aap.svg
newsroom/static/logo.svg
newsroom/static/menu.png
newsroom/static/meta_icon.png
newsroom/static/search_clear.png
newsroom/static/search_icon.png
newsroom/static/vertical_dots.png
newsroom/static/watermark.png
newsroom/static/wire_item_select.png
newsroom/static/dist/cards_js.dc469f2c5c7b3b58f6b2.js
newsroom/static/dist/cards_js.f36bf311dcf5de326a31.js
newsroom/static/dist/common.d8e4ea86b7013fb5928b.js
